dominions/__init__.py
dominions/__main__.py
dominions/core.py
dominions/dominions.py
dominions/whoisds.py
dominions/utils/__init__.py
dominions/utils/logger.py
dominions/utils/version.py
dominions-0.0.3.dist-info/LICENSE.md
dominions-0.0.3.dist-info/METADATA
dominions-0.0.3.dist-info/WHEEL
dominions-0.0.3.dist-info/entry_points.txt
dominions-0.0.3.dist-info/top_level.txt
dominions-0.0.3.dist-info/RECORD
