Metadata-Version: 2.1
Name: dominions
Version: 0.0.3
Summary: A Python package to check a domain against confusables, levenshtein distance, and more using a single interface. A Python package created using carcass
Home-page: https://github.com/swimlane/dominions
Author: MSAdministrator
Author-email: rickardja@live.com
License: MIT
Keywords: carcass
Platform: UNKNOWN
Requires-Python: >=3.6, <4
Requires-Dist: fire (==0.3.1)
Requires-Dist: requests (==2.25.1)
Requires-Dist: pendulum (==2.1.2)
Requires-Dist: confusables (==1.2.0)
Requires-Dist: python-Levenshtein (==0.12.2)
Requires-Dist: PyYAML (==5.4.1)
